[{"maxAlokasiKursi":9,"minAlokasiKursi":5,"dapil":[{"wilayah":[{"id":5255,"idDapil":1594,"idWilayah":13318,"createdBy":"nita","createdAt":"Dec 31, 2017 4:08:12 AM","updatedBy":"nita","updatedAt":"Dec 31, 2017 4:08:12 AM","namaWilayah":"TANJUNG MUTIARA","urutanWilayahDapil":1,"flagInclude":true},{"id":5256,"idDapil":1594,"idWilayah":13322,"createdBy":"nita","createdAt":"Dec 31, 2017 4:08:12 AM","updatedBy":"nita","updatedAt":"Dec 31, 2017 4:08:12 AM","namaWilayah":"LUBUK BASUNG","urutanWilayahDapil":2,"flagInclude":true}],"id":1594,"nama":"AGAM 1","parent":-1,"tingkat":2,"jumlahPenduduk":111962,"alokasiKursi":9,"sisaPenduduk":6986,"peringkatPenduduk":5,"alokasiSisaKursi":0,"idWilayah":13317,"createdBy":"nita","createdAt":"Dec 31, 2017 4:08:12 AM","updatedBy":"nita","updatedAt":"Dec 31, 2017 4:08:12 AM","totalAlokasiKursi":9,"idVersi":471,"noDapil":1,"statusCoterminous":false},{"wilayah":[{"id":5257,"idDapil":1595,"idWilayah":13385,"createdBy":"nita","createdAt":"Dec 31, 2017 4:08:12 AM","updatedBy":"nita","updatedAt":"Dec 31, 2017 4:08:12 AM","namaWilayah":"PELEMBAYAN","urutanWilayahDapil":1,"flagInclude":true},{"id":5258,"idDapil":1595,"idWilayah":13398,"createdBy":"nita","createdAt":"Dec 31, 2017 4:08:12 AM","updatedBy":"nita","updatedAt":"Dec 31, 2017 4:08:12 AM","namaWilayah":"AMPEK NAGARI","urutanWilayahDapil":2,"flagInclude":true}],"id":1595,"nama":"AGAM 2","parent":-1,"tingkat":2,"jumlahPenduduk":68165,"alokasiKursi":5,"sisaPenduduk":9845,"peringkatPenduduk":2,"alokasiSisaKursi":1,"idWilayah":13317,"createdBy":"nita","createdAt":"Dec 31, 2017 4:08:12 AM","updatedBy":"nita","updatedAt":"Dec 31, 2017 4:08:12 AM","totalAlokasiKursi":6,"idVersi":471,"noDapil":2,"statusCoterminous":false},{"wilayah":[{"id":5259,"idDapil":1596,"idWilayah":13376,"createdBy":"nita","createdAt":"Dec 31, 2017 4:08:12 AM","updatedBy":"nita","updatedAt":"Dec 31, 2017 4:08:12 AM","namaWilayah":"TILATANG KAMANG","urutanWilayahDapil":1,"flagInclude":true},{"id":5260,"idDapil":1596,"idWilayah":13380,"createdBy":"nita","createdAt":"Dec 31, 2017 4:08:12 AM","updatedBy":"nita","updatedAt":"Dec 31, 2017 4:08:12 AM","namaWilayah":"PALUPUH","urutanWilayahDapil":2,"flagInclude":true},{"id":5261,"idDapil":1596,"idWilayah":13407,"createdBy":"nita","createdAt":"Dec 31, 2017 4:08:12 AM","updatedBy":"nita","updatedAt":"Dec 31, 2017 4:08:12 AM","namaWilayah":"KAMANG MAGEK","urutanWilayahDapil":3,"flagInclude":true}],"id":1596,"nama":"AGAM 3","parent":-1,"tingkat":2,"jumlahPenduduk":77390,"alokasiKursi":6,"sisaPenduduk":7406,"peringkatPenduduk":4,"alokasiSisaKursi":1,"idWilayah":13317,"createdBy":"nita","createdAt":"Dec 31, 2017 4:08:12 AM","updatedBy":"nita","updatedAt":"Dec 31, 2017 4:08:12 AM","totalAlokasiKursi":7,"idVersi":471,"noDapil":3,"statusCoterminous":false},{"wilayah":[{"id":5262,"idDapil":1597,"idWilayah":13361,"createdBy":"nita","createdAt":"Dec 31, 2017 4:08:12 AM","updatedBy":"nita","updatedAt":"Dec 31, 2017 4:08:12 AM","namaWilayah":"AMPEK ANGKEK","urutanWilayahDapil":1,"flagInclude":true},{"id":5263,"idDapil":1597,"idWilayah":13369,"createdBy":"nita","createdAt":"Dec 31, 2017 4:08:12 AM","updatedBy":"nita","updatedAt":"Dec 31, 2017 4:08:12 AM","namaWilayah":"BASO","urutanWilayahDapil":2,"flagInclude":true},{"id":5264,"idDapil":1597,"idWilayah":13403,"createdBy":"nita","createdAt":"Dec 31, 2017 4:08:12 AM","updatedBy":"nita","updatedAt":"Dec 31, 2017 4:08:12 AM","namaWilayah":"CANDUNG","urutanWilayahDapil":3,"flagInclude":true}],"id":1597,"nama":"AGAM 4","parent":-1,"tingkat":2,"jumlahPenduduk":107698,"alokasiKursi":9,"sisaPenduduk":2722,"peringkatPenduduk":6,"alokasiSisaKursi":0,"idWilayah":13317,"createdBy":"nita","createdAt":"Dec 31, 2017 4:08:12 AM","updatedBy":"nita","updatedAt":"Dec 31, 2017 4:08:12 AM","totalAlokasiKursi":9,"idVersi":471,"noDapil":4,"statusCoterminous":false},{"wilayah":[{"id":5265,"idDapil":1598,"idWilayah":13392,"createdBy":"nita","createdAt":"Dec 31, 2017 4:08:12 AM","updatedBy":"nita","updatedAt":"Dec 31, 2017 4:08:12 AM","namaWilayah":"SUNGAI PUA","urutanWilayahDapil":1,"flagInclude":true},{"id":5266,"idDapil":1598,"idWilayah":13345,"createdBy":"nita","createdAt":"Dec 31, 2017 4:08:12 AM","updatedBy":"nita","updatedAt":"Dec 31, 2017 4:08:12 AM","namaWilayah":"IV KOTO","urutanWilayahDapil":2,"flagInclude":true},{"id":5267,"idDapil":1598,"idWilayah":13353,"createdBy":"nita","createdAt":"Dec 31, 2017 4:08:12 AM","updatedBy":"nita","updatedAt":"Dec 31, 2017 4:08:12 AM","namaWilayah":"BANUHAMPU","urutanWilayahDapil":3,"flagInclude":true},{"id":5268,"idDapil":1598,"idWilayah":13411,"createdBy":"nita","createdAt":"Dec 31, 2017 4:08:12 AM","updatedBy":"nita","updatedAt":"Dec 31, 2017 4:08:12 AM","namaWilayah":"MALALAK","urutanWilayahDapil":4,"flagInclude":true}],"id":1598,"nama":"AGAM 5","parent":-1,"tingkat":2,"jumlahPenduduk":102836,"alokasiKursi":8,"sisaPenduduk":9524,"peringkatPenduduk":3,"alokasiSisaKursi":1,"idWilayah":13317,"createdBy":"nita","createdAt":"Dec 31, 2017 4:08:12 AM","updatedBy":"nita","updatedAt":"Dec 31, 2017 4:08:12 AM","totalAlokasiKursi":9,"idVersi":471,"noDapil":5,"statusCoterminous":false},{"wilayah":[{"id":5269,"idDapil":1599,"idWilayah":13328,"createdBy":"nita","createdAt":"Dec 31, 2017 4:08:12 AM","updatedBy":"nita","updatedAt":"Dec 31, 2017 4:08:12 AM","namaWilayah":"TANJUNG RAYA","urutanWilayahDapil":1,"flagInclude":true},{"id":5270,"idDapil":1599,"idWilayah":13338,"createdBy":"nita","createdAt":"Dec 31, 2017 4:08:12 AM","updatedBy":"nita","updatedAt":"Dec 31, 2017 4:08:12 AM","namaWilayah":"MATUR","urutanWilayahDapil":2,"flagInclude":true}],"id":1599,"nama":"AGAM 6","parent":-1,"tingkat":2,"jumlahPenduduk":56855,"alokasiKursi":4,"sisaPenduduk":10199,"peringkatPenduduk":1,"alokasiSisaKursi":1,"idWilayah":13317,"createdBy":"nita","createdAt":"Dec 31, 2017 4:08:12 AM","updatedBy":"nita","updatedAt":"Dec 31, 2017 4:08:12 AM","totalAlokasiKursi":5,"idVersi":471,"noDapil":6,"statusCoterminous":false}],"id":471,"tingkat":2,"versi":1,"stdDev":1.6072751268321592,"mean":7.5,"statusVersi":1,"idWilayah":13317,"dapilOwner":1}]