[{"maxAlokasiKursi":9,"minAlokasiKursi":8,"dapil":[{"wilayah":[{"id":20950,"idDapil":6360,"idWilayah":71210,"createdBy":"vici","createdAt":"Mar 25, 2018 10:52:46 PM","namaWilayah":"PANCA LAUTANG","urutanWilayahDapil":1,"flagInclude":true},{"id":20951,"idDapil":6360,"idWilayah":71221,"createdBy":"vici","createdAt":"Mar 25, 2018 10:52:46 PM","namaWilayah":"TELLU LIMPOE","urutanWilayahDapil":2,"flagInclude":true},{"id":20952,"idDapil":6360,"idWilayah":71231,"createdBy":"vici","createdAt":"Mar 25, 2018 10:52:46 PM","namaWilayah":"WATANG PULU","urutanWilayahDapil":3,"flagInclude":true}],"id":6360,"nama":"SIDENRENG RAPPANG 1","parent":-1,"tingkat":2,"jumlahPenduduk":77898,"alokasiKursi":8,"sisaPenduduk":6930,"peringkatPenduduk":1,"alokasiSisaKursi":1,"idWilayah":71209,"createdBy":"vici","createdAt":"Dec 31, 2017 7:53:23 AM","updatedBy":"rita","updatedAt":"Dec 31, 2017 7:53:23 AM","totalAlokasiKursi":9,"idVersi":1524,"noDapil":1,"statusCoterminous":false},{"wilayah":[{"id":20953,"idDapil":6361,"idWilayah":71261,"createdBy":"vici","createdAt":"Mar 25, 2018 10:52:46 PM","namaWilayah":"KULO","urutanWilayahDapil":1,"flagInclude":true},{"id":20954,"idDapil":6361,"idWilayah":71242,"createdBy":"vici","createdAt":"Mar 25, 2018 10:52:46 PM","namaWilayah":"BARANTI","urutanWilayahDapil":2,"flagInclude":true},{"id":20955,"idDapil":6361,"idWilayah":71252,"createdBy":"vici","createdAt":"Mar 25, 2018 10:52:46 PM","namaWilayah":"PANCA RIJANG","urutanWilayahDapil":3,"flagInclude":true}],"id":6361,"nama":"SIDENRENG RAPPANG 2","parent":-1,"tingkat":2,"jumlahPenduduk":76694,"alokasiKursi":8,"sisaPenduduk":5726,"peringkatPenduduk":2,"alokasiSisaKursi":1,"idWilayah":71209,"createdBy":"vici","createdAt":"Dec 31, 2017 7:53:23 AM","updatedBy":"rita","updatedAt":"Dec 31, 2017 7:53:23 AM","totalAlokasiKursi":9,"idVersi":1524,"noDapil":2,"statusCoterminous":false},{"wilayah":[{"id":20956,"idDapil":6362,"idWilayah":71290,"createdBy":"vici","createdAt":"Mar 25, 2018 10:52:46 PM","namaWilayah":"DUA PITUE","urutanWilayahDapil":1,"flagInclude":true},{"id":20957,"idDapil":6362,"idWilayah":71314,"createdBy":"vici","createdAt":"Mar 25, 2018 10:52:46 PM","namaWilayah":"PITU RIASE","urutanWilayahDapil":2,"flagInclude":true},{"id":20958,"idDapil":6362,"idWilayah":71301,"createdBy":"vici","createdAt":"Mar 25, 2018 10:52:46 PM","namaWilayah":"PITU RIAWA","urutanWilayahDapil":3,"flagInclude":true}],"id":6362,"nama":"SIDENRENG RAPPANG 3","parent":-1,"tingkat":2,"jumlahPenduduk":83554,"alokasiKursi":9,"sisaPenduduk":3715,"peringkatPenduduk":3,"alokasiSisaKursi":0,"idWilayah":71209,"createdBy":"vici","createdAt":"Dec 31, 2017 7:53:22 AM","updatedBy":"rita","updatedAt":"Dec 31, 2017 7:53:22 AM","totalAlokasiKursi":9,"idVersi":1524,"noDapil":3,"statusCoterminous":false},{"wilayah":[{"id":20959,"idDapil":6363,"idWilayah":71268,"createdBy":"vici","createdAt":"Mar 25, 2018 10:52:46 PM","namaWilayah":"MARITENGNGAE","urutanWilayahDapil":1,"flagInclude":true},{"id":20960,"idDapil":6363,"idWilayah":71281,"createdBy":"vici","createdAt":"Mar 25, 2018 10:52:46 PM","namaWilayah":"WT. SIDENRENG","urutanWilayahDapil":2,"flagInclude":true}],"id":6363,"nama":"SIDENRENG RAPPANG 4","parent":-1,"tingkat":2,"jumlahPenduduk":72347,"alokasiKursi":8,"sisaPenduduk":1379,"peringkatPenduduk":4,"alokasiSisaKursi":0,"idWilayah":71209,"createdBy":"vici","createdAt":"Dec 31, 2017 7:53:22 AM","updatedBy":"rita","updatedAt":"Dec 31, 2017 7:53:22 AM","totalAlokasiKursi":8,"idVersi":1524,"noDapil":4,"statusCoterminous":false}],"id":1524,"tingkat":2,"versi":4,"stdDev":0.4330127018922193,"mean":8.75,"statusVersi":1,"idWilayah":71209}]