[{"maxAlokasiKursi":9,"minAlokasiKursi":7,"dapil":[{"wilayah":[{"id":22168,"idDapil":6708,"idWilayah":68608,"createdBy":"rita","createdAt":"Mar 28, 2018 3:43:03 PM","namaWilayah":"BUNGKU BARAT","urutanWilayahDapil":1,"flagInclude":true},{"id":22169,"idDapil":6708,"idWilayah":68525,"createdBy":"rita","createdAt":"Mar 28, 2018 3:43:03 PM","namaWilayah":"BUNGKU TENGAH","urutanWilayahDapil":2,"flagInclude":true},{"id":22170,"idDapil":6708,"idWilayah":83805,"createdBy":"rita","createdAt":"Mar 28, 2018 3:43:03 PM","namaWilayah":"BUNGKU TIMUR","urutanWilayahDapil":3,"flagInclude":true}],"id":6708,"nama":"MOROWALI 1","parent":-1,"tingkat":2,"jumlahPenduduk":48792,"alokasiKursi":9,"sisaPenduduk":2064,"peringkatPenduduk":3,"alokasiSisaKursi":0,"idWilayah":68428,"createdBy":"rita","createdAt":"Dec 31, 2017 2:34:19 PM","updatedBy":"rita","updatedAt":"Dec 31, 2017 2:34:19 PM","totalAlokasiKursi":9,"idVersi":1600,"noDapil":1,"statusCoterminous":false},{"wilayah":[{"id":22171,"idDapil":6709,"idWilayah":68633,"createdBy":"rita","createdAt":"Mar 28, 2018 3:43:03 PM","namaWilayah":"BAHODOPI","urutanWilayahDapil":1,"flagInclude":true},{"id":22172,"idDapil":6709,"idWilayah":83802,"createdBy":"rita","createdAt":"Mar 28, 2018 3:43:03 PM","namaWilayah":"BUNGKU PESISIR","urutanWilayahDapil":2,"flagInclude":true},{"id":22173,"idDapil":6709,"idWilayah":68555,"createdBy":"rita","createdAt":"Mar 28, 2018 3:43:03 PM","namaWilayah":"BUNGKU SELATAN","urutanWilayahDapil":3,"flagInclude":true},{"id":22174,"idDapil":6709,"idWilayah":68589,"createdBy":"rita","createdAt":"Mar 28, 2018 3:43:03 PM","namaWilayah":"MENUI KEPULAUAN","urutanWilayahDapil":4,"flagInclude":true}],"id":6709,"nama":"MOROWALI 2","parent":-1,"tingkat":2,"jumlahPenduduk":45669,"alokasiKursi":8,"sisaPenduduk":4133,"peringkatPenduduk":2,"alokasiSisaKursi":1,"idWilayah":68428,"createdBy":"rita","createdAt":"Dec 31, 2017 2:34:19 PM","updatedBy":"rita","updatedAt":"Dec 31, 2017 2:34:19 PM","totalAlokasiKursi":9,"idVersi":1600,"noDapil":2,"statusCoterminous":false},{"wilayah":[{"id":22175,"idDapil":6710,"idWilayah":68619,"createdBy":"rita","createdAt":"Mar 28, 2018 3:43:03 PM","namaWilayah":"BUMI RAYA","urutanWilayahDapil":1,"flagInclude":true},{"id":22176,"idDapil":6710,"idWilayah":68656,"createdBy":"rita","createdAt":"Mar 28, 2018 3:43:03 PM","namaWilayah":"WITA PONDA","urutanWilayahDapil":2,"flagInclude":true}],"id":6710,"nama":"MOROWALI 3","parent":-1,"tingkat":2,"jumlahPenduduk":35353,"alokasiKursi":6,"sisaPenduduk":4201,"peringkatPenduduk":1,"alokasiSisaKursi":1,"idWilayah":68428,"createdBy":"rita","createdAt":"Dec 31, 2017 2:34:19 PM","updatedBy":"rita","updatedAt":"Dec 31, 2017 2:34:19 PM","totalAlokasiKursi":7,"idVersi":1600,"noDapil":3,"statusCoterminous":false}],"id":1600,"tingkat":2,"versi":2,"stdDev":0.9428090415820634,"mean":8.333333333333334,"statusVersi":1,"idWilayah":68428}]