[{"maxAlokasiKursi":9,"minAlokasiKursi":6,"dapil":[{"wilayah":[{"id":14412,"idDapil":4452,"idWilayah":56036,"createdBy":"hafizh","createdAt":"Dec 31, 2017 4:53:27 PM","updatedBy":"hafizh","updatedAt":"Dec 31, 2017 4:53:27 PM","namaWilayah":"ATAMBUA SELATAN","urutanWilayahDapil":1,"flagInclude":true},{"id":14413,"idDapil":4452,"idWilayah":55947,"createdBy":"hafizh","createdAt":"Dec 31, 2017 4:53:27 PM","updatedBy":"hafizh","updatedAt":"Dec 31, 2017 4:53:27 PM","namaWilayah":"KOTA ATAMBUA","urutanWilayahDapil":2,"flagInclude":true}],"id":4452,"nama":"BELU 1","parent":-1,"tingkat":2,"jumlahPenduduk":59828,"alokasiKursi":8,"sisaPenduduk":980,"peringkatPenduduk":4,"alokasiSisaKursi":0,"idWilayah":55819,"createdBy":"hafizh","createdAt":"Dec 31, 2017 4:53:27 PM","updatedBy":"hafizh","updatedAt":"Dec 31, 2017 4:53:27 PM","totalAlokasiKursi":8,"idVersi":1125,"noDapil":1,"statusCoterminous":false},{"wilayah":[{"id":14414,"idDapil":4453,"idWilayah":56031,"createdBy":"hafizh","createdAt":"Dec 31, 2017 4:53:27 PM","updatedBy":"hafizh","updatedAt":"Dec 31, 2017 4:53:27 PM","namaWilayah":"ATAMBUA BARAT","urutanWilayahDapil":1,"flagInclude":true},{"id":14415,"idDapil":4453,"idWilayah":55859,"createdBy":"hafizh","createdAt":"Dec 31, 2017 4:53:27 PM","updatedBy":"hafizh","updatedAt":"Dec 31, 2017 4:53:27 PM","namaWilayah":"KAKULUK MESAK","urutanWilayahDapil":2,"flagInclude":true}],"id":4453,"nama":"BELU 2","parent":-1,"tingkat":2,"jumlahPenduduk":47941,"alokasiKursi":6,"sisaPenduduk":3805,"peringkatPenduduk":2,"alokasiSisaKursi":1,"idWilayah":55819,"createdBy":"hafizh","createdAt":"Dec 31, 2017 4:53:27 PM","updatedBy":"hafizh","updatedAt":"Dec 31, 2017 4:53:27 PM","totalAlokasiKursi":7,"idVersi":1125,"noDapil":2,"statusCoterminous":false},{"wilayah":[{"id":14416,"idDapil":4454,"idWilayah":55820,"createdBy":"hafizh","createdAt":"Dec 31, 2017 4:53:27 PM","updatedBy":"hafizh","updatedAt":"Dec 31, 2017 4:53:27 PM","namaWilayah":"LAMAKNEN","urutanWilayahDapil":1,"flagInclude":true},{"id":14417,"idDapil":4454,"idWilayah":56008,"createdBy":"hafizh","createdAt":"Dec 31, 2017 4:53:27 PM","updatedBy":"hafizh","updatedAt":"Dec 31, 2017 4:53:27 PM","namaWilayah":"LAMAKNEN SELATAN","urutanWilayahDapil":2,"flagInclude":true},{"id":14418,"idDapil":4454,"idWilayah":56000,"createdBy":"hafizh","createdAt":"Dec 31, 2017 4:53:27 PM","updatedBy":"hafizh","updatedAt":"Dec 31, 2017 4:53:27 PM","namaWilayah":"LASIOLAT","urutanWilayahDapil":3,"flagInclude":true},{"id":14419,"idDapil":4454,"idWilayah":55843,"createdBy":"hafizh","createdAt":"Dec 31, 2017 4:53:27 PM","updatedBy":"hafizh","updatedAt":"Dec 31, 2017 4:53:27 PM","namaWilayah":"RAIHAT","urutanWilayahDapil":4,"flagInclude":true},{"id":14420,"idDapil":4454,"idWilayah":55830,"createdBy":"hafizh","createdAt":"Dec 31, 2017 4:53:27 PM","updatedBy":"hafizh","updatedAt":"Dec 31, 2017 4:53:27 PM","namaWilayah":"TASIFETOTIMUR","urutanWilayahDapil":5,"flagInclude":true}],"id":4454,"nama":"BELU 3","parent":-1,"tingkat":2,"jumlahPenduduk":65770,"alokasiKursi":8,"sisaPenduduk":6922,"peringkatPenduduk":1,"alokasiSisaKursi":1,"idWilayah":55819,"createdBy":"hafizh","createdAt":"Dec 31, 2017 4:53:27 PM","updatedBy":"hafizh","updatedAt":"Dec 31, 2017 4:53:27 PM","totalAlokasiKursi":9,"idVersi":1125,"noDapil":3,"statusCoterminous":false},{"wilayah":[{"id":14421,"idDapil":4455,"idWilayah":56041,"createdBy":"hafizh","createdAt":"Dec 31, 2017 4:53:27 PM","updatedBy":"hafizh","updatedAt":"Dec 31, 2017 4:53:27 PM","namaWilayah":"NANAET DUABESI","urutanWilayahDapil":1,"flagInclude":true},{"id":14422,"idDapil":4455,"idWilayah":55952,"createdBy":"hafizh","createdAt":"Dec 31, 2017 4:53:27 PM","updatedBy":"hafizh","updatedAt":"Dec 31, 2017 4:53:27 PM","namaWilayah":"RAIMANUK","urutanWilayahDapil":2,"flagInclude":true},{"id":14423,"idDapil":4455,"idWilayah":55850,"createdBy":"hafizh","createdAt":"Dec 31, 2017 4:53:27 PM","updatedBy":"hafizh","updatedAt":"Dec 31, 2017 4:53:27 PM","namaWilayah":"TASIFETO BARAT","urutanWilayahDapil":3,"flagInclude":true}],"id":4455,"nama":"BELU 4","parent":-1,"tingkat":2,"jumlahPenduduk":47160,"alokasiKursi":6,"sisaPenduduk":3024,"peringkatPenduduk":3,"alokasiSisaKursi":0,"idWilayah":55819,"createdBy":"hafizh","createdAt":"Dec 31, 2017 4:53:27 PM","updatedBy":"hafizh","updatedAt":"Dec 31, 2017 4:53:27 PM","totalAlokasiKursi":6,"idVersi":1125,"noDapil":4,"statusCoterminous":false}],"id":1125,"tingkat":2,"versi":1,"stdDev":1.118033988749895,"mean":7.5,"statusVersi":1,"idWilayah":55819,"dapilOwner":1}]