[{"maxAlokasiKursi":8,"minAlokasiKursi":3,"dapil":[{"wilayah":[{"id":290,"idDapil":58,"idWilayah":54853,"createdBy":"superadmin","createdAt":"Jan 22, 2018 1:36:31 PM","updatedAt":"Jan 22, 2018 1:36:31 PM","namaWilayah":"SUMBAWA BARAT","urutanWilayahDapil":1,"flagInclude":true},{"id":287,"idDapil":58,"idWilayah":54400,"createdBy":"superadmin","createdAt":"Jan 22, 2018 1:36:31 PM","updatedAt":"Jan 22, 2018 1:36:31 PM","namaWilayah":"SUMBAWA","urutanWilayahDapil":2,"flagInclude":true},{"id":288,"idDapil":58,"idWilayah":54590,"createdBy":"superadmin","createdAt":"Jan 22, 2018 1:36:31 PM","updatedAt":"Jan 22, 2018 1:36:31 PM","namaWilayah":"DOMPU","urutanWilayahDapil":3,"flagInclude":true},{"id":289,"idDapil":58,"idWilayah":54666,"createdBy":"superadmin","createdAt":"Jan 22, 2018 1:36:31 PM","updatedAt":"Jan 22, 2018 1:36:31 PM","namaWilayah":"BIMA","urutanWilayahDapil":4,"flagInclude":true},{"id":292,"idDapil":58,"idWilayah":54982,"createdBy":"superadmin","createdAt":"Jan 22, 2018 1:36:31 PM","updatedAt":"Jan 22, 2018 1:36:31 PM","namaWilayah":"KOTA BIMA","urutanWilayahDapil":5,"flagInclude":true}],"id":58,"nama":"NUSA TENGGARA BARAT I","tingkat":0,"jumlahPenduduk":-1,"idWilayah":54020,"createdBy":"superadmin","createdAt":"Jan 22, 2018 1:16:36 PM","updatedAt":"Jan 22, 2018 1:16:36 PM","totalAlokasiKursi":3,"idVersi":87,"noDapil":1,"statusCoterminous":true},{"wilayah":[{"id":284,"idDapil":59,"idWilayah":54021,"createdBy":"superadmin","createdAt":"Jan 22, 2018 1:36:31 PM","updatedAt":"Jan 22, 2018 1:36:31 PM","namaWilayah":"LOMBOK BARAT","urutanWilayahDapil":1,"flagInclude":true},{"id":285,"idDapil":59,"idWilayah":54123,"createdBy":"superadmin","createdAt":"Jan 22, 2018 1:36:31 PM","updatedAt":"Jan 22, 2018 1:36:31 PM","namaWilayah":"LOMBOK TENGAH","urutanWilayahDapil":2,"flagInclude":true},{"id":286,"idDapil":59,"idWilayah":54260,"createdBy":"superadmin","createdAt":"Jan 22, 2018 1:36:31 PM","updatedAt":"Jan 22, 2018 1:36:31 PM","namaWilayah":"LOMBOK TIMUR","urutanWilayahDapil":3,"flagInclude":true},{"id":293,"idDapil":59,"idWilayah":55026,"createdBy":"superadmin","createdAt":"Jan 22, 2018 1:36:31 PM","updatedAt":"Jan 22, 2018 1:36:31 PM","namaWilayah":"LOMBOK UTARA","urutanWilayahDapil":4,"flagInclude":true},{"id":291,"idDapil":59,"idWilayah":54925,"createdBy":"superadmin","createdAt":"Jan 22, 2018 1:36:31 PM","updatedAt":"Jan 22, 2018 1:36:31 PM","namaWilayah":"KOTA MATARAM","urutanWilayahDapil":5,"flagInclude":true}],"id":59,"nama":"NUSA TENGGARA BARAT II","tingkat":0,"jumlahPenduduk":-1,"idWilayah":54020,"createdBy":"superadmin","createdAt":"Jan 22, 2018 1:16:36 PM","updatedAt":"Jan 22, 2018 1:16:36 PM","totalAlokasiKursi":8,"idVersi":87,"noDapil":2,"statusCoterminous":true}],"id":87,"tingkat":0,"versi":1,"stdDev":2.5,"mean":5.5,"statusVersi":1,"idWilayah":54020}]